{"TRANSACTION_ID": "TXN-a12ae9c1", "TIMESTAMP": "2025-05-18T00:25:00.647026Z", "USER_ID_HASHED": "5c088227086b573e6929a11c4ae621e7", "USER_NAME_HASHED": "81d6f316d169150d0e8733866c38684d", "PRODUCT_ID": "PROD-188", "AMOUNT": 186.1, "CURRENCY": "EUR", "TRANSACTION_TYPE": "refund", "STATUS": "pending", "CITY": "Nagoya", "COUNTRY": "Japan", "PAYMENT_METHOD": "cryptocurrency", "PRODUCT_CATEGORY": "home_goods", "QUANTITY": 9, "SHIPPING_STREET": "755 Main St", "SHIPPING_ZIP": "10492", "SHIPPING_CITY": "Nagoya", "SHIPPING_COUNTRY": "Japan", "DEVICE_OS": "MacOS", "DEVICE_BROWSER": "Chrome", "MASKED_IP": "110.37.2xxx.xxx", "CUSTOMER_RATING": null, "DISCOUNT_CODE": null, "TAX_AMOUNT": 0.0, "THREAD": null, "MESSAGE_NUMBER": null, "TIMESTAMP_OF_RECEPTION_LOG": null, "AMOUNT_USD": 200.988}