{"TRANSACTION_ID": "TXN-204c0e0b", "TIMESTAMP": "2025-05-18T00:24:57.596687Z", "USER_ID_HASHED": "272b04ed520ce1bcdcb67462d0d57948", "USER_NAME_HASHED": "59830e37ce261d31ad0da0d5d270d0e1", "PRODUCT_ID": "PROD-510", "AMOUNT": 507.0, "CURRENCY": "USD", "TRANSACTION_TYPE": "withdrawal", "STATUS": "cancelled", "CITY": "Chicago", "COUNTRY": "USA", "PAYMENT_METHOD": "apple_pay", "PRODUCT_CATEGORY": "books", "QUANTITY": 10, "SHIPPING_STREET": "998 Main St", "SHIPPING_ZIP": "80452", "SHIPPING_CITY": "Chicago", "SHIPPING_COUNTRY": "USA", "DEVICE_OS": "Windows", "DEVICE_BROWSER": "Chrome", "MASKED_IP": "89.249.1xxx.xxx", "CUSTOMER_RATING": null, "DISCOUNT_CODE": null, "TAX_AMOUNT": 0.0, "THREAD": null, "MESSAGE_NUMBER": null, "TIMESTAMP_OF_RECEPTION_LOG": null, "AMOUNT_USD": 507.0}