{"transaction_id": "TXN-169d3325", "timestamp": "2025-05-18T00:24:19.932238Z", "user_id": "USER-9568", "user_name": "Thomas", "product_id": "PROD-103", "amount": 261.48, "currency": "AUD", "transaction_type": "purchase", "status": "cancelled", "location": {"city": "Rio de Janeiro", "country": "Brazil"}, "payment_method": "bank_transfer", "product_category": "home_goods", "quantity": 3, "shipping_address": {"street": "507 Main St", "zip": "24182", "city": "Rio de Janeiro", "country": "Brazil"}, "device_info": {"os": "Windows", "browser": "Chrome", "ip_address": "74.144.40.117"}, "customer_rating": 3, "discount_code": "DISCOUNT-605", "tax_amount": 0.0, "thread_id": 1, "sent_at": "2025-05-18T00:24:19.932444Z"}