{"transaction_id": "TXN-55c3be26", "timestamp": "2025-05-18T00:24:34.965613Z", "user_id": "USER-6730", "user_name": "Jones", "product_id": "PROD-613", "amount": 256.7, "currency": "JPY", "transaction_type": "purchase", "status": "completed", "location": {"city": "Nice", "country": "France"}, "payment_method": "paypal", "product_category": "electronics", "quantity": 2, "shipping_address": {"street": "288 Main St", "zip": "47749", "city": "Nice", "country": "France"}, "device_info": {"os": "Windows", "browser": "Firefox", "ip_address": "195.110.226.92"}, "customer_rating": 3, "discount_code": "DISCOUNT-327", "tax_amount": 26.89, "thread_id": 4, "sent_at": "2025-05-18T00:24:34.965831Z"}