{"transaction_id": "TXN-876b1eb3", "timestamp": "2025-05-18T00:25:04.632351Z", "user_id": "USER-7601", "user_name": "Hernandez", "product_id": "PROD-854", "amount": 215.74, "currency": "CAD", "transaction_type": "refund", "status": "completed", "location": {"city": "Paris", "country": "France"}, "payment_method": "bank_transfer", "product_category": "food", "quantity": 2, "shipping_address": {"street": "178 Main St", "zip": "95028", "city": "Paris", "country": "France"}, "device_info": {"os": "iOS", "browser": "Chrome", "ip_address": "167.133.187.79"}, "customer_rating": 3, "discount_code": "DISCOUNT-353", "tax_amount": 21.47, "thread_id": 3, "sent_at": "2025-05-18T00:25:04.632596Z"}