{"transaction_id": "TXN-8bd20426", "timestamp": "2025-05-18T00:25:06.706450Z", "user_id": "USER-3096", "user_name": "Martin", "product_id": "PROD-476", "amount": 943.16, "currency": "GBP", "transaction_type": "purchase", "status": "cancelled", "location": {"city": "Osaka", "country": "Japan"}, "payment_method": "paypal", "product_category": "clothing", "quantity": 1, "shipping_address": {"street": "289 Main St", "zip": "91217", "city": "Osaka", "country": "Japan"}, "device_info": {"os": "iOS", "browser": "Firefox", "ip_address": "135.167.50.99"}, "customer_rating": 5, "discount_code": null, "tax_amount": 0.0, "thread_id": 0, "sent_at": "2025-05-18T00:25:06.706516Z"}