{"transaction_id": "TXN-207402c3", "timestamp": "2025-05-18T00:24:56.093047Z", "user_id": "USER-4653", "user_name": "Anderson", "product_id": "PROD-706", "amount": 692.6, "currency": "JPY", "transaction_type": "purchase", "status": "cancelled", "location": {"city": "Toulouse", "country": "France"}, "payment_method": "cryptocurrency", "product_category": "clothing", "quantity": 2, "shipping_address": {"street": "682 Main St", "zip": "63412", "city": "Toulouse", "country": "France"}, "device_info": {"os": "MacOS", "browser": "Edge", "ip_address": "173.3.41.126"}, "customer_rating": null, "discount_code": "DISCOUNT-559", "tax_amount": 0.0, "thread_id": 3, "sent_at": "2025-05-18T00:24:56.093192Z"}