{"transaction_id": "TXN-d83a392f", "timestamp": "2025-05-18T00:24:44.105470Z", "user_id": "USER-7026", "user_name": "Perez", "product_id": "PROD-558", "amount": 240.92, "currency": "EUR", "transaction_type": "refund", "status": "failed", "location": {"city": "Marseille", "country": "France"}, "payment_method": "cryptocurrency", "product_category": "books", "quantity": 4, "shipping_address": {"street": "772 Main St", "zip": "15296", "city": "Marseille", "country": "France"}, "device_info": {"os": "iOS", "browser": "Firefox", "ip_address": "60.37.88.39"}, "customer_rating": null, "discount_code": null, "tax_amount": 0.0, "thread_id": 0, "sent_at": "2025-05-18T00:24:44.105657Z"}