{"transaction_id": "TXN-835878d2", "timestamp": "2025-05-18T00:24:27.492307Z", "user_id": "USER-3721", "user_name": "Williams", "product_id": "PROD-566", "amount": 969.68, "currency": "USD", "transaction_type": "refund", "status": "cancelled", "location": {"city": "Osaka", "country": "Japan"}, "payment_method": "bank_transfer", "product_category": "books", "quantity": 5, "shipping_address": {"street": "496 Main St", "zip": "79955", "city": "Osaka", "country": "Japan"}, "device_info": {"os": "Windows", "browser": "Safari", "ip_address": "227.63.40.218"}, "customer_rating": null, "discount_code": "DISCOUNT-874", "tax_amount": 0.0, "thread_id": 2, "sent_at": "2025-05-18T00:24:27.492403Z"}