{"transaction_id": "TXN-ef8af78e", "timestamp": "2025-05-18T00:24:33.030100Z", "user_id": "USER-6106", "user_name": "Lee", "product_id": "PROD-540", "amount": 472.74, "currency": "CAD", "transaction_type": "withdrawal", "status": "processing", "location": {"city": "Toulouse", "country": "France"}, "payment_method": "paypal", "product_category": "clothing", "quantity": 3, "shipping_address": {"street": "739 Main St", "zip": "74178", "city": "Toulouse", "country": "France"}, "device_info": {"os": "iOS", "browser": "Firefox", "ip_address": "133.1.76.141"}, "customer_rating": 3, "discount_code": null, "tax_amount": 0.0, "thread_id": 0, "sent_at": "2025-05-18T00:24:33.030219Z"}