{"transaction_id": "TXN-dadcffcc", "timestamp": "2025-05-18T00:25:00.615735Z", "user_id": "USER-2473", "user_name": "Williams", "product_id": "PROD-892", "amount": 161.38, "currency": "CAD", "transaction_type": "withdrawal", "status": "cancelled", "location": {"city": "Phoenix", "country": "USA"}, "payment_method": "google_pay", "product_category": "food", "quantity": 3, "shipping_address": {"street": "299 Main St", "zip": "59515", "city": "Phoenix", "country": "USA"}, "device_info": {"os": "iOS", "browser": "Firefox", "ip_address": "97.192.103.177"}, "customer_rating": null, "discount_code": null, "tax_amount": 0.0, "thread_id": 3, "sent_at": "2025-05-18T00:25:00.615789Z"}