{"transaction_id": "TXN-bf37e115", "timestamp": "2025-05-18T00:24:43.006487Z", "user_id": "USER-4788", "user_name": "Hernandez", "product_id": "PROD-135", "amount": 673.52, "currency": "EUR", "transaction_type": "refund", "status": "completed", "location": {"city": "Frankfurt", "country": "Germany"}, "payment_method": "paypal", "product_category": "electronics", "quantity": 5, "shipping_address": {"street": "167 Main St", "zip": "43470", "city": "Frankfurt", "country": "Germany"}, "device_info": {"os": "Android", "browser": "Firefox", "ip_address": "252.103.148.65"}, "customer_rating": null, "discount_code": "DISCOUNT-192", "tax_amount": 116.87, "thread_id": 4, "sent_at": "2025-05-18T00:24:43.006692Z"}