{"TRANSACTION_ID": "TXN-e7c0512b", "TIMESTAMP": "2025-05-18T00:25:13.671471Z", "USER_ID_HASHED": "8cdde96f4e7431ab826fbd1c74321579", "USER_NAME_HASHED": "81d6f316d169150d0e8733866c38684d", "PRODUCT_ID": "PROD-997", "AMOUNT": 578.15, "CURRENCY": "USD", "TRANSACTION_TYPE": "payment", "STATUS": "processing", "CITY": "Beijing", "COUNTRY": "China", "PAYMENT_METHOD": "paypal", "PRODUCT_CATEGORY": "clothing", "QUANTITY": 5, "SHIPPING_STREET": "154 Main St", "SHIPPING_ZIP": "64761", "SHIPPING_CITY": "Beijing", "SHIPPING_COUNTRY": "China", "DEVICE_OS": "Linux", "DEVICE_BROWSER": "Chrome", "MASKED_IP": "151.113.xxx.xxx", "CUSTOMER_RATING": null, "DISCOUNT_CODE": "DISCOUNT-783", "TAX_AMOUNT": 0.0, "THREAD": null, "MESSAGE_NUMBER": null, "TIMESTAMP_OF_RECEPTION_LOG": null}