{"TRANSACTION_ID": "TXN-4d625671", "TIMESTAMP": "2025-05-18T00:24:59.139038Z", "USER_ID_HASHED": "858bfffe15934e5b5a734270b7202b4c", "USER_NAME_HASHED": "3f84183918bbcce913eecb6fd74a27d0", "PRODUCT_ID": "PROD-940", "AMOUNT": 250.04, "CURRENCY": "CAD", "TRANSACTION_TYPE": "payment", "STATUS": "failed", "CITY": "Chicago", "COUNTRY": "USA", "PAYMENT_METHOD": "credit_card", "PRODUCT_CATEGORY": "clothing", "QUANTITY": 4, "SHIPPING_STREET": "266 Main St", "SHIPPING_ZIP": "65185", "SHIPPING_CITY": "Chicago", "SHIPPING_COUNTRY": "USA", "DEVICE_OS": "Windows", "DEVICE_BROWSER": "Edge", "MASKED_IP": "215.145.xxx.xxx", "CUSTOMER_RATING": 1, "DISCOUNT_CODE": null, "TAX_AMOUNT": 0.0, "THREAD": null, "MESSAGE_NUMBER": null, "TIMESTAMP_OF_RECEPTION_LOG": null, "AMOUNT_USD": 187.53}