{"TRANSACTION_ID": "TXN-1a619dfb", "TIMESTAMP": "2025-05-18T00:25:01.575667Z", "USER_ID_HASHED": "4ddd91e6837d9a7bf4bb5dfe017f5039", "USER_NAME_HASHED": "56c052be7cc218dbc1a4092a9db64c50", "PRODUCT_ID": "PROD-380", "AMOUNT": 253.28, "CURRENCY": "JPY", "TRANSACTION_TYPE": "withdrawal", "STATUS": "pending", "CITY": "Nagoya", "COUNTRY": "Japan", "PAYMENT_METHOD": "bank_transfer", "PRODUCT_CATEGORY": "clothing", "QUANTITY": 4, "SHIPPING_STREET": "808 Main St", "SHIPPING_ZIP": "79757", "SHIPPING_CITY": "Nagoya", "SHIPPING_COUNTRY": "Japan", "DEVICE_OS": "Linux", "DEVICE_BROWSER": "Edge", "MASKED_IP": "217.157.xxx.xxx", "CUSTOMER_RATING": 3, "DISCOUNT_CODE": null, "TAX_AMOUNT": 0.0, "THREAD": null, "MESSAGE_NUMBER": null, "TIMESTAMP_OF_RECEPTION_LOG": null, "AMOUNT_USD": 1.77296}